chrisjen/__init__.py
chrisjen/core/framework.py
chrisjen/core/keystones.py
chrisjen/core/nodes.py
chrisjen/options/design.py
chrisjen/options/export.py
chrisjen/options/librarians.py
chrisjen/options/managers.py
chrisjen/options/repository.py
chrisjen/options/represent.py
chrisjen/options/research.py
chrisjen/options/stages.py
chrisjen/options/supervisers.py
chrisjen/options/tasks.py
chrisjen/options/validators.py
chrisjen/options/views.py
chrisjen/options/workers.py
chrisjen/options/workflows.py
chrisjen/options/workshop.py
chrisjen-0.1.3.dist-info/LICENSE
chrisjen-0.1.3.dist-info/WHEEL
chrisjen-0.1.3.dist-info/METADATA
chrisjen-0.1.3.dist-info/RECORD
