Metadata-Version: 2.1
Name: chrisjen
Version: 0.1.3
Summary: Python project workflows made easy
Home-page: https://github.com/WithPrecedent/chrisjen
License: Apache-2.0
Author: Corey Rayburn Yung
Author-email: coreyrayburnyung@gmail.com
Requires-Python: >=3.9,<4.0
Classifier: License :: OSI Approved :: Apache Software License
Classifier: Programming Language :: Python :: 3
Classifier: Programming Language :: Python :: 3.9
Classifier: Programming Language :: Python :: 3.10
Requires-Dist: bobbie (>=0.1.1,<0.2.0)
Requires-Dist: camina (>=0.1.10,<0.2.0)
Requires-Dist: holden (>=0.1.5,<0.2.0)
Requires-Dist: miller (>=0.1.5,<0.2.0)
Requires-Dist: more_itertools (>=9.0.0,<10.0.0)
Requires-Dist: nagata (>=0.1.3,<0.2.0)
Project-URL: Repository, https://github.com/WithPrecedent/chrisjen
